typecoverage/__init__.py
typecoverage/__main__.py
typecoverage/core.py
typecoverage-1.0.1.dist-info/licenses/LICENSE
typecoverage-1.0.1.dist-info/METADATA
typecoverage-1.0.1.dist-info/WHEEL
typecoverage-1.0.1.dist-info/entry_points.txt
typecoverage-1.0.1.dist-info/top_level.txt
typecoverage-1.0.1.dist-info/RECORD
