Metadata-Version: 2.4
Name: typecoverage
Version: 1.0.1
Summary: A strict CLI + library API to report untyped variables, arguments, and function returns in Python code
Home-page: https://github.com/kairos-xx/typecoverage
Author: Joao Lopes
Author-email: Joao Lopes <joaslopes@gmail.com>
Maintainer: Joao Lopes
Maintainer-email: Joao Lopes <joaslopes@gmail.com>
License: 
Project-URL: Homepage, https://github.com/kairos-xx/typecoverage
Project-URL: Repository, https://github.com/kairos-xx/typecoverage
Project-URL: Documentation, https://github.com/kairos-xx/typecoverage/docs
Project-URL: Issues, https://github.com/kairos-xx/typecoverage/issues
Project-URL: Changelog, https://github.com/kairos-xx/typecoverage/releases
Keywords: type-checking,static-analysis,type-annotations,code-quality,python-typing,ast-analysis
Platform: any
Classifier: Development Status :: 5 - Production/Stable
Classifier: Intended Audience :: Developers
Classifier: Intended Audience :: Science/Research
Classifier: License :: OSI Approved :: MIT License
Classifier: Programming Language :: Python :: 3
Classifier: Programming Language :: Python :: 3.11
Classifier: Programming Language :: Python :: 3.12
Classifier: Operating System :: OS Independent
Classifier: Natural Language :: English
Classifier: Typing :: Typed
Classifier: Topic :: Software Development :: Libraries :: Python Modules
Classifier: Topic :: Software Development :: Quality Assurance
Classifier: Topic :: Software Development :: Testing
Classifier: Topic :: Software Development :: Code Generators
Classifier: Topic :: Software Development :: Debuggers
Classifier: Environment :: Console
Classifier: Environment :: Web Environment
Requires-Python: >=3.11
License-File: LICENSE
Requires-Dist: pytest>=7.0.0
Requires-Dist: replit==4.1.0
Requires-Dist: black
Requires-Dist: flake8
Requires-Dist: build
Requires-Dist: requests
Requires-Dist: pyright
Requires-Dist: toml
Requires-Dist: pyyaml
Requires-Dist: isort
Requires-Dist: pyproject-flake8
Requires-Dist: zipfile38==0.0.3
Provides-Extra: dev
Requires-Dist: pytest-cov; extra == "dev"
Requires-Dist: pytest-xdist; extra == "dev"
Requires-Dist: mypy; extra == "dev"
Requires-Dist: ruff; extra == "dev"
Requires-Dist: pre-commit; extra == "dev"
Provides-Extra: test
Requires-Dist: pytest>=7.0.0; extra == "test"
Requires-Dist: pytest-cov; extra == "test"
Requires-Dist: coverage[toml]; extra == "test"
Dynamic: author
Dynamic: home-page
Dynamic: license-file
Dynamic: maintainer
Dynamic: platform
Dynamic: requires-python
